colloquy_chatbot/__init__.py
colloquy_chatbot/chat_bot.py
colloquy_chatbot/claude_bot.py
colloquy_chatbot/echo_bot.py
colloquy_chatbot/openai_bot.py
colloquy_chatbot/prompt_function.py
colloquy_chatbot-0.1.0.dist-info/METADATA
colloquy_chatbot-0.1.0.dist-info/WHEEL
colloquy_chatbot-0.1.0.dist-info/top_level.txt
colloquy_chatbot-0.1.0.dist-info/RECORD
