Metadata-Version: 2.1
Name: colloquy_chatbot
Version: 0.1.0
Summary: A more intuitive and consistent interface on top of existing chatbot APIs
Author-email: Colin Williams <lackita@gmail.com>
License: MIT
Project-URL: Homepage, https://github.com/Colloquy-ChatBot/colloquy-python
Project-URL: Bug Tracker, https://github.com/Colloquy-ChatBot/colloquy-python/issues
Requires-Python: >=3.8
Requires-Dist: openai>=1.0.0
Requires-Dist: anthropic>=0.3.0
Provides-Extra: dev
Requires-Dist: pytest>=7.0.0; extra == "dev"
Requires-Dist: pytest-asyncio>=0.21.0; extra == "dev"
Requires-Dist: black>=23.0.0; extra == "dev"
Requires-Dist: isort>=5.0.0; extra == "dev"
Requires-Dist: mypy>=1.0.0; extra == "dev"
